text2svg.libs/libcairo-411c042f.so.2.10800.8
text2svg.libs/libpangoft2-1-567fa780.0.so.0.2800.1
text2svg.libs/libpixman-1-b2de6761.so.0.32.8
text2svg.libs/libexpat-64fa60ba.so.1.5.2
text2svg.libs/libfontconfig-63352676.so.1.4.4
text2svg.libs/libpango-1-7b7caade.0.so.0.2800.1
text2svg.libs/libpangocairo-1-35b5d57c.0.so.0.2800.1
text2svg.libs/libpng12-640ca796.so.0.49.0
text2svg.libs/libz-eb09ad1d.so.1.2.3
text2svg.libs/libgmodule-2-bac48ce7.0.so.0.2800.8
text2svg.libs/libfreetype-20bfc0cd.so.6.3.22
text2svg-0.3.0.dist-info/WHEEL
text2svg-0.3.0.dist-info/entry_points.txt
text2svg-0.3.0.dist-info/LICENSE
text2svg-0.3.0.dist-info/RECORD
text2svg-0.3.0.dist-info/top_level.txt
text2svg-0.3.0.dist-info/METADATA
text2svg/__version__.py
text2svg/cli.py
text2svg/__init__.py
text2svg/__main__.py
text2svg/settings.py
text2svg/ctext2svg.cpython-38-x86_64-linux-gnu.so
