Metadata-Version: 2.1
Name: text2svg
Version: 0.3.0
Summary: Convert text to SVG file.
Home-page: https://text2svg.syrusdark.website
Author: Naveen M K
Author-email: naveen@syrusdark.website
Maintainer: Naveen M K
Maintainer-email: naveen@syrusdark.website
License: GPL version 3
Project-URL: Issue tracker, https://github.com/naveen521kk/text2svg/issues
Project-URL: Documentation, https://text2svg.syrusdark.website
Project-URL: Download, https://pypi.org/project/text2svg
Project-URL: Code, https://github.com/naveen521kk/text2svg
Keywords: cython,pango,cairo,svg
Platform: Linux
Platform: macOS
Platform: Windows
Classifier: Programming Language :: Python :: 3
Classifier: Development Status :: 3 - Alpha
Classifier: License :: OSI Approved :: GNU General Public License v3 (GPLv3)
Classifier: Operating System :: OS Independent
Classifier: Programming Language :: Cython
Requires-Python: >=3.6
Provides-Extra: cli
Requires-Dist: colorama ; extra == 'cli'
